README.md
setup.py
src/nasrl/__init__.py
src/nasrl/nn.py
src/nasrl/replay.py
src/nasrl/reward.py
src/nasrl/task.py
src/nasrl.egg-info/PKG-INFO
src/nasrl.egg-info/SOURCES.txt
src/nasrl.egg-info/dependency_links.txt
src/nasrl.egg-info/top_level.txt
src/nasrl/field/__init__.py
src/nasrl/field/conf.py
src/nasrl/field/field.py
src/nasrl/field/transform.py
src/nasrl/tree/__init__.py
src/nasrl/tree/actions.py
src/nasrl/tree/actor.py
src/nasrl/tree/env.py
src/nasrl/tree/nodes.py
src/nasrl/tree/policy.py
src/nasrl/tree/ptree.py