Metadata-Version: 1.2
Name: nasrl
Version: 0.2.2
Summary: Library code for our NAS-RL project.
Home-page: UNKNOWN
Author: Matthew McRaven
Author-email: mkm302@georgetown.edu
License: UNKNOWN
Platform: UNKNOWN
Requires-Python: ~= 3.8
